config_ninja/__init__.py
config_ninja/__main__.py
config_ninja/backend.py
config_ninja/cli.md
config_ninja/cli.py
config_ninja/contrib/__init__.py
config_ninja/contrib/appconfig.py
config_ninja/contrib/local.py
config_ninja/contrib/secretsmanager.py
config_ninja/controller.py
config_ninja/hooks.py
config_ninja/settings/__init__.py
config_ninja/settings/schema.py
config_ninja/systemd.py
config_ninja/templates/systemd.service.j2
config_ninja-2.0.2.dist-info/METADATA
config_ninja-2.0.2.dist-info/WHEEL
config_ninja-2.0.2.dist-info/entry_points.txt
config_ninja-2.0.2.dist-info/licenses/LICENSE.md
config_ninja-2.0.2.dist-info/RECORD
