Metadata-Version: 2.4
Name: config-ninja
Version: 2.0.2
Summary: Use special ninja powers to manage system configurations 🥷
License-File: LICENSE.md
Author: Bryant Finney
Author-email: <bryant.finney@outlook.com>
Requires-Python: >=3.9,<4
Classifier: Intended Audience :: Developers
Classifier: License :: OSI Approved :: MIT License
Classifier: Operating System :: OS Independent
Classifier: Programming Language :: Python :: 3 :: Only
Classifier: Programming Language :: Python :: 3.10
Classifier: Programming Language :: Python :: 3.11
Classifier: Programming Language :: Python :: 3.12
Classifier: Programming Language :: Python :: 3.13
Classifier: Programming Language :: Python :: 3.9
Classifier: Programming Language :: Python
Classifier: Typing :: Typed
Provides-Extra: all
Provides-Extra: appconfig
Provides-Extra: local
Provides-Extra: poe
Requires-Dist: boto3 (>=1.34,<2.0) ; extra == "all"
Requires-Dist: boto3 (>=1.34,<2.0) ; extra == "appconfig"
Requires-Dist: jinja2 (>3.1.4,<4.0)
Requires-Dist: poethepoet (>=0.29,<0.31) ; extra == "all"
Requires-Dist: poethepoet (>=0.29,<0.31) ; extra == "poe"
Requires-Dist: pyspry (>=1.0.2,<1.1.0)
Requires-Dist: pyyaml (>=6.0,<7.0)
Requires-Dist: sdnotify (>=0.3.2,<0.4.0)
Requires-Dist: sh (>=2.0,<3.0) ; sys_platform != "win32"
Requires-Dist: tomlkit (>=0.12.3,<0.14.0)
Requires-Dist: typer (>=0.9,<0.16)
Requires-Dist: typing-extensions (>=4.7,<5.0) ; python_version < "3.11"
Requires-Dist: watchfiles (>=0.21,<0.25) ; extra == "all"
Requires-Dist: watchfiles (>=0.21,<0.25) ; extra == "local"
Project-URL: Documentation, https://config-ninja.github.io/config-ninja/config_ninja.html
Project-URL: Homepage, https://github.com/config-ninja/config-ninja
Project-URL: changelog, https://github.com/config-ninja/config-ninja/releases
Project-URL: issues, https://github.com/config-ninja/config-ninja/issues
Project-URL: readthedocs, https://config-ninja.readthedocs.org/home.html
Project-URL: source, https://github.com/config-ninja/config-ninja
